pywoudc/__init__.py
pywoudc/__pycache__/__init__.cpython-311.pyc
pywoudc-0.3.1.dist-info/LICENSE
pywoudc-0.3.1.dist-info/METADATA
pywoudc-0.3.1.dist-info/WHEEL
pywoudc-0.3.1.dist-info/entry_points.txt
pywoudc-0.3.1.dist-info/top_level.txt
pywoudc-0.3.1.dist-info/RECORD
