Metadata-Version: 2.1
Name: pywoudc
Version: 0.3.1
Summary: High level package providing Pythonic access to WMO WOUDC data services
Home-page: https://github.com/woudc/pywoudc
Author: Tom Kralidis
Author-email: tomkralidis@gmail.com
Maintainer: Tom Kralidis
Maintainer-email: tomkraldis@gmail.com
License: MIT
Keywords: woudc ozone uv ultra-violet atmosphere atmospheric composition WMO
Platform: all
Classifier: Development Status :: 4 - Beta
Classifier: Environment :: Console
Classifier: Intended Audience :: Developers
Classifier: Intended Audience :: Science/Research
Classifier: License :: OSI Approved :: MIT License
Classifier: Operating System :: OS Independent
Classifier: Programming Language :: Python
Classifier: Topic :: Scientific/Engineering :: Atmospheric Science
Classifier: Topic :: Scientific/Engineering :: GIS
License-File: LICENSE
Requires-Dist: click
Requires-Dist: OWSLib
Requires-Dist: prettytable
